gvgen.py
GvGen-1.0.dist-info/LICENSE
GvGen-1.0.dist-info/METADATA
GvGen-1.0.dist-info/WHEEL
GvGen-1.0.dist-info/top_level.txt
GvGen-1.0.dist-info/RECORD
