Metadata-Version: 2.1
Name: GvGen
Version: 1.0
Summary: Generate clear Graphviz Graphs which can be edited manually later on.
Home-page: http://www.github.com/stricaud/gvgen/
Author: Sebastien Tricaud
Author-email: sebastien@honeynet.org
License: UNKNOWN
Platform: UNKNOWN
Classifier: Programming Language :: Python :: 3
Classifier: License :: OSI Approved :: MIT License
Classifier: Operating System :: OS Independent
